btcspv/__init__.py
btcspv/py.typed
btcspv/ser.py
btcspv/types.py
btcspv/utils.py
btcspv/validate_spv.py
bitcoin_spv_py-3.0.1.dist-info/METADATA
bitcoin_spv_py-3.0.1.dist-info/WHEEL
bitcoin_spv_py-3.0.1.dist-info/top_level.txt
bitcoin_spv_py-3.0.1.dist-info/RECORD
