Metadata-Version: 2.1
Name: bitcoin-spv-py
Version: 3.0.1
Summary: UNKNOWN
Home-page: https://github.com/summa-tx/bitcoin-spv
Author: James Prestwich
Author-email: james@summa.one
License: UNKNOWN
Platform: UNKNOWN
Classifier: License :: OSI Approved :: GNU Lesser General Public License v3 (LGPLv3)
Requires-Python: >=3.6
Requires-Dist: riemann-tx (==2.1.0)
